README.rst
setup.py
silo.py
silo.egg-info/PKG-INFO
silo.egg-info/SOURCES.txt
silo.egg-info/dependency_links.txt
silo.egg-info/top_level.txt