Metadata-Version: 1.1
Name: silo
Version: 0.2
Summary: Simply Logging
Home-page: https://github.com/digitalmensch/silo
Author: Tobias Ammann
Author-email: UNKNOWN
License: MIT
Download-URL: https://pypi.python.org/pypi/silo
Keywords: logging,simple,json,audit
Platform: any
Classifier: Development Status :: 4 - Beta
Classifier: Intended Audience :: Developers
Classifier: License :: OSI Approved :: MIT License
Classifier: Operating System :: OS Independent
Classifier: Programming Language :: Python
Classifier: Programming Language :: Python :: 3.6
Classifier: Topic :: Database :: Front-Ends
